object_status/__init__.py
object_status/admin.py
object_status/apps.py
object_status/models.py
object_status/tests.py
object_status/utils.py
object_status/static/object_status/js/status_color.js
object_status/templates/admin/change_form.html
object_status/templates/admin/change_list.html
django_object_status-0.1.dist-info/LICENSE
django_object_status-0.1.dist-info/METADATA
django_object_status-0.1.dist-info/WHEEL
django_object_status-0.1.dist-info/top_level.txt
django_object_status-0.1.dist-info/RECORD
