Metadata-Version: 2.1
Name: django-object-status
Version: 0.1
Summary: A Django app for managing a model object review process
Home-page: https://github.com/zachtylr21/django-object-status
Author: Zach Taylor
Author-email: zachtylr04@gmail.com
License: BSD-2-Clause
Download-URL: https://github.com/zachtylr21/django-object-status/archive/v0.1.tar.gz
Platform: UNKNOWN
Classifier: Environment :: Web Environment
Classifier: Framework :: Django
Classifier: Framework :: Django :: 2.2
Classifier: Intended Audience :: Developers
Classifier: License :: OSI Approved :: BSD License
Classifier: Operating System :: OS Independent
Classifier: Programming Language :: Python
Classifier: Programming Language :: Python :: 3.6
Classifier: Programming Language :: Python :: 3.7
Classifier: Topic :: Internet :: WWW/HTTP
Classifier: Topic :: Internet :: WWW/HTTP :: Dynamic Content
